gaterpc/__init__.py
gaterpc/core.py
gaterpc/exceptions.py
gaterpc/global_settings.py
gaterpc/log_handler.py
gaterpc/mixins.py
gaterpc/testBoundedDict.py
gaterpc/testMajordomo.py
gaterpc/utils.py
gaterpc-0.2.11.dist-info/LICENSE
gaterpc-0.2.11.dist-info/METADATA
gaterpc-0.2.11.dist-info/WHEEL
gaterpc-0.2.11.dist-info/top_level.txt
gaterpc-0.2.11.dist-info/RECORD
