Metadata-Version: 2.1
Name: gaterpc
Version: 0.2.11
Summary: A RPC software based on ZeroMQ with built-in Majordomo.
Home-page: https://github.com/firejoke/gate-rpc
Author: Shi Fan
Author-email: Shi Fan <firejokeshi@gmail.com>
License: BSD 3-Clause License
Project-URL: Repository, https://github.com/firejoke/gate-rpc
Keywords: zero,zeroMQ,rpc
Classifier: Development Status :: 4 - Beta
Classifier: License :: OSI Approved :: BSD License
Classifier: Programming Language :: Python :: 3.9
Requires-Python: >=3.9
License-File: LICENSE
Requires-Dist: msgpack>=1.0.7
Requires-Dist: pyzmq>=25.1.2
